 {"type" : "FeatureCollection", "features" : [{"type" : "Feature", "properties" : {"id":1,"location":"SERPENT_01-01","name":"I01","value":2.00,"year":2020}}, {"type" : "Feature", "properties" : {"id":2,"location":"SERPENT_01-02","name":"I01","value":2.00,"year":2020}}, {"type" : "Feature", "properties" : {"id":3,"location":"SERPENT_01-03","name":"I01","value":2.00,"year":2020}}, {"type" : "Feature", "properties" : {"id":4,"location":"SERPENT_01-04","name":"I01","value":1.50,"year":2020}}, {"type" : "Feature", "properties" : {"id":19,"location":"SERPENT_01_01","name":"I02","value":7.64,"year":2020}}, {"type" : "Feature", "properties" : {"id":20,"location":"SERPENT_01_02","name":"I02","value":6.56,"year":2020}}, {"type" : "Feature", "properties" : {"id":21,"location":"SERPENT_01_03","name":"I02","value":6.98,"year":2020}}, {"type" : "Feature", "properties" : {"id":22,"location":"SERPENT_01_04","name":"I02","value":6.78,"year":2020}}, {"type" : "Feature", "properties" : {"id":23,"location":"SERPENT_01_05","name":"I02","value":6.43,"year":2020}}, {"type" : "Feature", "properties" : {"id":24,"location":"SERPENT_01_06","name":"I02","value":6.22,"year":2020}}, {"type" : "Feature", "properties" : {"id":25,"location":"SERPENT_01_07","name":"I02","value":6.63,"year":2020}}, {"type" : "Feature", "properties" : {"id":26,"location":"SERPENT_01_08","name":"I02","value":6.77,"year":2020}}, {"type" : "Feature", "properties" : {"id":27,"location":"SERPENT_01_09","name":"I02","value":6.71,"year":2020}}, {"type" : "Feature", "properties" : {"id":28,"location":"SERPENT_02_01","name":"I02","value":7.18,"year":2020}}, {"type" : "Feature", "properties" : {"id":29,"location":"SERPENT_02_02","name":"I02","value":6.67,"year":2020}}, {"type" : "Feature", "properties" : {"id":30,"location":"SERPENT_02_03","name":"I02","value":7.29,"year":2020}}, {"type" : "Feature", "properties" : {"id":31,"location":"SERPENT_02_04","name":"I02","value":6.71,"year":2020}}, {"type" : "Feature", "properties" : {"id":32,"location":"SERPENT_02_05","name":"I02","value":6.39,"year":2020}}, {"type" : "Feature", "properties" : {"id":33,"location":"SERPENT_02_06","name":"I02","value":6.74,"year":2020}}, {"type" : "Feature", "properties" : {"id":34,"location":"SERPENT_02_07","name":"I02","value":6.87,"year":2020}}, {"type" : "Feature", "properties" : {"id":35,"location":"SERPENT_02_08","name":"I02","value":6.91,"year":2020}}, {"type" : "Feature", "properties" : {"id":36,"location":"SERPENT_02_09","name":"I02","value":6.58,"year":2020}}, {"type" : "Feature", "properties" : {"id":37,"location":"SERPENT_02_10","name":"I02","value":6.37,"year":2020}}, {"type" : "Feature", "properties" : {"id":38,"location":"SERPENT_02_11","name":"I02","value":6.83,"year":2020}}, {"type" : "Feature", "properties" : {"id":39,"location":"SERPENT_01_01","name":"I06","value":2.53,"year":2020}}, {"type" : "Feature", "properties" : {"id":40,"location":"SERPENT_01_02","name":"I06","value":2.26,"year":2020}}, {"type" : "Feature", "properties" : {"id":41,"location":"SERPENT_01_03","name":"I06","value":2.49,"year":2020}}, {"type" : "Feature", "properties" : {"id":42,"location":"SERPENT_01_04","name":"I06","value":2.48,"year":2020}}, {"type" : "Feature", "properties" : {"id":43,"location":"SERPENT_01_05","name":"I06","value":2.37,"year":2020}}, {"type" : "Feature", "properties" : {"id":44,"location":"SERPENT_01_06","name":"I06","value":2.39,"year":2020}}, {"type" : "Feature", "properties" : {"id":45,"location":"SERPENT_01_07","name":"I06","value":2.50,"year":2020}}, {"type" : "Feature", "properties" : {"id":46,"location":"SERPENT_01_08","name":"I06","value":2.46,"year":2020}}, {"type" : "Feature", "properties" : {"id":47,"location":"SERPENT_01_09","name":"I06","value":2.51,"year":2020}}, {"type" : "Feature", "properties" : {"id":48,"location":"SERPENT_02_01","name":"I06","value":2.77,"year":2020}}, {"type" : "Feature", "properties" : {"id":49,"location":"SERPENT_02_02","name":"I06","value":2.70,"year":2020}}, {"type" : "Feature", "properties" : {"id":50,"location":"SERPENT_02_03","name":"I06","value":2.28,"year":2020}}, {"type" : "Feature", "properties" : {"id":51,"location":"SERPENT_02_04","name":"I06","value":2.27,"year":2020}}, {"type" : "Feature", "properties" : {"id":52,"location":"SERPENT_02_05","name":"I06","value":2.54,"year":2020}}, {"type" : "Feature", "properties" : {"id":53,"location":"SERPENT_02_06","name":"I06","value":2.72,"year":2020}}, {"type" : "Feature", "properties" : {"id":54,"location":"SERPENT_02_07","name":"I06","value":2.71,"year":2020}}, {"type" : "Feature", "properties" : {"id":55,"location":"SERPENT_02_08","name":"I06","value":2.47,"year":2020}}, {"type" : "Feature", "properties" : {"id":56,"location":"SERPENT_02_09","name":"I06","value":2.55,"year":2020}}, {"type" : "Feature", "properties" : {"id":57,"location":"SERPENT_02_10","name":"I06","value":2.33,"year":2020}}, {"type" : "Feature", "properties" : {"id":58,"location":"SERPENT_02_11","name":"I06","value":2.45,"year":2020}}, {"type" : "Feature", "properties" : {"id":59,"location":"SERPENT_01_01","name":"I08","value":25.90,"year":2020}}, {"type" : "Feature", "properties" : {"id":60,"location":"SERPENT_01_02","name":"I08","value":23.34,"year":2020}}, {"type" : "Feature", "properties" : {"id":61,"location":"SERPENT_01_03","name":"I08","value":25.07,"year":2020}}, {"type" : "Feature", "properties" : {"id":62,"location":"SERPENT_01_04","name":"I08","value":25.46,"year":2020}}, {"type" : "Feature", "properties" : {"id":63,"location":"SERPENT_01_05","name":"I08","value":27.74,"year":2020}}, {"type" : "Feature", "properties" : {"id":64,"location":"SERPENT_01_06","name":"I08","value":22.04,"year":2020}}, {"type" : "Feature", "properties" : {"id":65,"location":"SERPENT_01_07","name":"I08","value":24.91,"year":2020}}, {"type" : "Feature", "properties" : {"id":66,"location":"SERPENT_01_08","name":"I08","value":23.83,"year":2020}}, {"type" : "Feature", "properties" : {"id":67,"location":"SERPENT_01_09","name":"I08","value":22.77,"year":2020}}, {"type" : "Feature", "properties" : {"id":68,"location":"SERPENT_02_01","name":"I08","value":27.35,"year":2020}}, {"type" : "Feature", "properties" : {"id":69,"location":"SERPENT_02_02","name":"I08","value":23.78,"year":2020}}, {"type" : "Feature", "properties" : {"id":70,"location":"SERPENT_02_03","name":"I08","value":21.79,"year":2020}}, {"type" : "Feature", "properties" : {"id":71,"location":"SERPENT_02_04","name":"I08","value":24.35,"year":2020}}, {"type" : "Feature", "properties" : {"id":72,"location":"SERPENT_02_05","name":"I08","value":25.37,"year":2020}}, {"type" : "Feature", "properties" : {"id":73,"location":"SERPENT_02_06","name":"I08","value":19.24,"year":2020}}, {"type" : "Feature", "properties" : {"id":74,"location":"SERPENT_02_07","name":"I08","value":23.66,"year":2020}}, {"type" : "Feature", "properties" : {"id":75,"location":"SERPENT_02_08","name":"I08","value":25.09,"year":2020}}, {"type" : "Feature", "properties" : {"id":76,"location":"SERPENT_02_09","name":"I08","value":20.32,"year":2020}}, {"type" : "Feature", "properties" : {"id":77,"location":"SERPENT_02_10","name":"I08","value":19.53,"year":2020}}, {"type" : "Feature", "properties" : {"id":78,"location":"SERPENT_02_11","name":"I08","value":21.41,"year":2020}}, {"type" : "Feature", "properties" : {"id":79,"location":"MADONE_02_01","name":"I01","value":4.00,"year":2020}}, {"type" : "Feature", "properties" : {"id":80,"location":"MADONE_02_02","name":"I01","value":3.00,"year":2020}}, {"type" : "Feature", "properties" : {"id":81,"location":"MADONE_02_03","name":"I01","value":3.00,"year":2020}}, {"type" : "Feature", "properties" : {"id":82,"location":"MADONE_02_01","name":"I02","value":6.00,"year":2020}}, {"type" : "Feature", "properties" : {"id":83,"location":"MADONE_02_02","name":"I02","value":5.56,"year":2020}}, {"type" : "Feature", "properties" : {"id":84,"location":"MADONE_02_03","name":"I02","value":6.41,"year":2020}}, {"type" : "Feature", "properties" : {"id":85,"location":"MADONE_02_04","name":"I02","value":5.92,"year":2020}}, {"type" : "Feature", "properties" : {"id":86,"location":"MADONE_02_05","name":"I02","value":6.22,"year":2020}}, {"type" : "Feature", "properties" : {"id":87,"location":"MADONE_02_01","name":"I06","value":2.93,"year":2020}}, {"type" : "Feature", "properties" : {"id":88,"location":"MADONE_02_02","name":"I06","value":2.00,"year":2020}}, {"type" : "Feature", "properties" : {"id":89,"location":"MADONE_02_03","name":"I06","value":2.31,"year":2020}}, {"type" : "Feature", "properties" : {"id":90,"location":"MADONE_02_04","name":"I06","value":2.25,"year":2020}}, {"type" : "Feature", "properties" : {"id":91,"location":"MADONE_02_05","name":"I06","value":2.67,"year":2020}}, {"type" : "Feature", "properties" : {"id":92,"location":"MADONE_02_01","name":"I08","value":8.29,"year":2020}}, {"type" : "Feature", "properties" : {"id":93,"location":"MADONE_02_02","name":"I08","value":5.12,"year":2020}}, {"type" : "Feature", "properties" : {"id":94,"location":"MADONE_02_03","name":"I08","value":14.07,"year":2020}}, {"type" : "Feature", "properties" : {"id":95,"location":"MADONE_02_04","name":"I08","value":13.44,"year":2020}}, {"type" : "Feature", "properties" : {"id":96,"location":"MADONE_02_05","name":"I08","value":13.67,"year":2020}}]}

